pymoth/__init__.py
pymoth/main.py
pymoth/MNIST_all/MNIST_make_all.py
pymoth/MNIST_all/__init__.py
pymoth/modules/classify.py
pymoth/modules/generate.py
pymoth/modules/params.py
pymoth/modules/sde.py
pymoth/modules/show_figs.py
mothnet-0.0.5.dist-info/METADATA
mothnet-0.0.5.dist-info/WHEEL
mothnet-0.0.5.dist-info/top_level.txt
mothnet-0.0.5.dist-info/RECORD
