Metadata-Version: 2.1
Name: mothnet
Version: 0.0.5
Summary: Neural network modeled after the olfactory system of the hawkmoth.
Home-page: https://github.com/meccaLeccaHi/pymoth
Author: Adam Jones
Author-email: ajones173@gmail.com
License: MIT
Platform: UNKNOWN
Classifier: Programming Language :: Python :: 3.6
Classifier: License :: OSI Approved :: MIT License
Classifier: Operating System :: OS Independent
Requires-Dist: matplotlib
Requires-Dist: scikit-learn
Requires-Dist: scikit-image
Requires-Dist: pillow
Requires-Dist: keras
Requires-Dist: tensorflow
